src/__init__.py
src/pychonk.py
pychonk-0.0.4.dist-info/LICENSE
pychonk-0.0.4.dist-info/METADATA
pychonk-0.0.4.dist-info/WHEEL
pychonk-0.0.4.dist-info/entry_points.txt
pychonk-0.0.4.dist-info/top_level.txt
pychonk-0.0.4.dist-info/RECORD
