Metadata-Version: 2.1
Name: pychonk
Version: 0.0.4
Summary: ranked disk-space used by each of your installed packages
Home-page: https://github.com/andytwoods/pychonk
Author: Andy Thomas Woods
Author-email: andytwoods@gmail.com
License: UNKNOWN
Platform: UNKNOWN
Classifier: Programming Language :: Python :: 3
Classifier: License :: OSI Approved :: MIT License
Classifier: Operating System :: OS Independent
Requires-Python: >=3
